timescaledb/__init__.py
timescaledb/activator.py
timescaledb/cleaners.py
timescaledb/compression/__init__.py
timescaledb/compression/add.py
timescaledb/compression/enable.py
timescaledb/compression/extractors.py
timescaledb/compression/sql.py
timescaledb/compression/sync.py
timescaledb/compression/validators.py
timescaledb/defaults.py
timescaledb/engine.py
timescaledb/exceptions.py
timescaledb/hyperfunctions/__init__.py
timescaledb/hyperfunctions/main.py
timescaledb/hypertables/__init__.py
timescaledb/hypertables/create.py
timescaledb/hypertables/extractors.py
timescaledb/hypertables/list.py
timescaledb/hypertables/schemas.py
timescaledb/hypertables/sql_statements.py
timescaledb/hypertables/sync.py
timescaledb/hypertables/validators.py
timescaledb/metadata.py
timescaledb/models.py
timescaledb/queries.py
timescaledb/retention/__init__.py
timescaledb/retention/add.py
timescaledb/retention/extractors.py
timescaledb/retention/sql.py
timescaledb/retention/sync.py
timescaledb/utils.py
timescaledb-0.0.3.dist-info/METADATA
timescaledb-0.0.3.dist-info/WHEEL
timescaledb-0.0.3.dist-info/entry_points.txt
timescaledb-0.0.3.dist-info/RECORD
