Metadata-Version: 2.3
Name: timescaledb
Version: 0.0.3
Summary: TimescaleDB is a Python Client based on SQLModel and SQLAlchemy for high-performance real-time analytics time-series data.
License: MIT
Keywords: TimescaleDB,SQLModel,SQLAlchemy,Time-Series,Analytics
Author: Justin Mitchel
Author-email: justin@codingforentrepreneurs.com
Requires-Python: >=3.11
Classifier: Development Status :: 4 - Beta
Classifier: Intended Audience :: Developers
Classifier: License :: OSI Approved :: MIT License
Classifier: Natural Language :: English
Classifier: Operating System :: OS Independent
Classifier: Programming Language :: Python :: 3 :: Only
Classifier: Programming Language :: Python :: 3.11
Classifier: Programming Language :: Python :: 3.12
Classifier: Programming Language :: Python :: 3.13
Classifier: Programming Language :: Python :: Implementation :: CPython
Requires-Dist: fastapi (>=0.104.0)
Requires-Dist: sqlmodel (>=0.0.8)
Requires-Dist: uvicorn (>=0.23.2)
Project-URL: Homepage, https://github.com/jmitchel3/timescaledb
Project-URL: Repository, https://github.com/jmitchel3/timescaledb
